setup.py
pyquality/__init__.py
pyquality/cli.py
pyquality/git_utils.py
pyquality/graphs.py
pyquality/main.py
pyquality/report.py
pyquality/template.py
pyquality/video.py
pyquality.egg-info/PKG-INFO
pyquality.egg-info/SOURCES.txt
pyquality.egg-info/dependency_links.txt
pyquality.egg-info/entry_points.txt
pyquality.egg-info/not-zip-safe
pyquality.egg-info/requires.txt
pyquality.egg-info/top_level.txt