Metadata-Version: 1.1
Name: pyquality
Version: 0.1.0
Summary: Rich reports for Python code quality
Home-page: https://github.com/NAMD/pyquality
Author: ('\xc3\x81lvaro Justen <alvarojusten@gmail.com>', 'Fl\xc3\xa1vio Amieiro <flavioamieiro@gmail.com>')
Author-email: alvarojusten@gmail.com
License: GPL
Keywords: code quality,pep8
Platform: UNKNOWN
Classifier: Development Status :: 3 - Alpha
Classifier: Intended Audience :: Developers
Classifier: License :: OSI Approved :: GNU General Public License (GPL)
Classifier: Programming Language :: Python :: 2.7
Classifier: Topic :: Software Development :: Libraries :: Python Modules
